ResistanceCurvature/__init__.py
ResistanceCurvature/resistance_curvature.py
resistancecurvature-0.0.0.1.dist-info/licenses/LICENSE
resistancecurvature-0.0.0.1.dist-info/METADATA
resistancecurvature-0.0.0.1.dist-info/WHEEL
resistancecurvature-0.0.0.1.dist-info/top_level.txt
resistancecurvature-0.0.0.1.dist-info/RECORD
