Metadata-Version: 2.4
Name: ResistanceCurvature
Version: 0.0.0.1
Summary: Calculate resistance curvature
Author: Chaoqun Fei, Tinglve Zhou, Yangyang Li
Author-email: 1079484353@qq.com
License: Apache-2.0
Keywords: python,Curvature,Resistance,Geometry,windows,mac,linux
Classifier: Intended Audience :: Developers
Classifier: Intended Audience :: Science/Research
Classifier: Programming Language :: Python :: 3
Classifier: Operating System :: POSIX :: Linux
Classifier: Operating System :: Microsoft :: Windows
Classifier: Topic :: Scientific/Engineering :: Artificial Intelligence
Classifier: Environment :: GPU :: NVIDIA CUDA
Requires-Python: >=3.8
License-File: LICENSE
Requires-Dist: torch>=1.10.0
Dynamic: author
Dynamic: author-email
Dynamic: classifier
Dynamic: description
Dynamic: description-content-type
Dynamic: keywords
Dynamic: license
Dynamic: license-file
Dynamic: requires-dist
Dynamic: requires-python
Dynamic: summary
